kmd_hmdb_api_client/__init__.py
kmd_hmdb_api_client/client.py
kmd_hmdb_api_client/errors.py
kmd_hmdb_api_client/types.py
kmd_hmdb_api_client/api/__init__.py
kmd_hmdb_api_client/api/compound/__init__.py
kmd_hmdb_api_client/api/compound/api_compound_create.py
kmd_hmdb_api_client/api/default/__init__.py
kmd_hmdb_api_client/api/default/api_annotation_find.py
kmd_hmdb_api_client/api/default/api_annotation_get.py
kmd_hmdb_api_client/api/default/api_compound_delete.py
kmd_hmdb_api_client/api/default/api_compound_find.py
kmd_hmdb_api_client/api/default/api_compound_get.py
kmd_hmdb_api_client/api/default/api_taxonomy_find.py
kmd_hmdb_api_client/api/default/api_taxonomy_get.py
kmd_hmdb_api_client/api/informations/__init__.py
kmd_hmdb_api_client/api/informations/api_about_info.py
kmd_hmdb_api_client/api/informations/api_about_specs.py
kmd_hmdb_api_client/api/informations/api_compound_stats.py
kmd_hmdb_api_client/models/__init__.py
kmd_hmdb_api_client/models/annotation.py
kmd_hmdb_api_client/models/compound.py
kmd_hmdb_api_client/models/error.py
kmd_hmdb_api_client/models/informations.py
kmd_hmdb_api_client/models/new_annotation.py
kmd_hmdb_api_client/models/new_compound.py
kmd_hmdb_api_client/models/new_taxonomy.py
kmd_hmdb_api_client/models/statistics.py
kmd_hmdb_api_client/models/statistics_taxonomies.py
kmd_hmdb_api_client/models/taxonomy.py
kmd_hmdb_api_client-1.0.1.dist-info/METADATA
kmd_hmdb_api_client-1.0.1.dist-info/WHEEL
kmd_hmdb_api_client-1.0.1.dist-info/top_level.txt
kmd_hmdb_api_client-1.0.1.dist-info/RECORD
