Metadata-Version: 2.1
Name: kmd-hmdb-api-client
Version: 1.0.1
Summary: A API Client for KMD HMDB
Home-page: 
Author: Lainou
Author-email: lain.pavot@inrae.fr
License: GNU GENERAL PUBLIC LICENSE v3
Classifier: Development Status :: 5 - Production/Stable
Classifier: Intended Audience :: Developers
Classifier: Natural Language :: English
Classifier: Operating System :: OS Independent
Classifier: Programming Language :: Python
Classifier: Programming Language :: Python :: 3
Classifier: Programming Language :: Python :: 3.9
Requires-Python: >=3.9.0
Requires-Dist: attrs ==23.1.0
Requires-Dist: click ==8.1.3
Requires-Dist: httpx ==0.24.1
